eb_features/__init__.py
eb_features/panel/__init__.py
eb_features/panel/calendar.py
eb_features/panel/config.py
eb_features/panel/constants.py
eb_features/panel/encoders.py
eb_features/panel/engineering.py
eb_features/panel/lags.py
eb_features/panel/rolling.py
eb_features/panel/validation.py
eb_features-0.2.5.dist-info/licenses/LICENSE
eb_features-0.2.5.dist-info/METADATA
eb_features-0.2.5.dist-info/WHEEL
eb_features-0.2.5.dist-info/top_level.txt
eb_features-0.2.5.dist-info/RECORD
