Metadata-Version: 2.4
Name: eb-features
Version: 0.2.5
Summary: Feature engineering utilities for panel time-series data in the Electric Barometer ecosystem.
Author-email: "Kyle Corrie (Economistician)" <kcorrie@economistician.com>
License-Expression: BSD-3-Clause
Project-URL: Homepage, https://github.com/Economistician/eb-features
Project-URL: Repository, https://github.com/Economistician/eb-features
Project-URL: Issues, https://github.com/Economistician/eb-features/issues
Project-URL: Documentation, https://economistician.github.io/eb-docs/
Keywords: forecasting,features,feature-engineering,time-series,panel-data,operations-research
Classifier: Development Status :: 3 - Alpha
Classifier: Intended Audience :: Science/Research
Classifier: Intended Audience :: Developers
Classifier: Programming Language :: Python :: 3
Classifier: Programming Language :: Python :: 3 :: Only
Classifier: Programming Language :: Python :: 3.10
Classifier: Programming Language :: Python :: 3.11
Classifier: Programming Language :: Python :: 3.12
Classifier: Programming Language :: Python :: 3.13
Classifier: Operating System :: OS Independent
Classifier: Topic :: Scientific/Engineering
Requires-Python: >=3.10
License-File: LICENSE
Requires-Dist: numpy>=1.24
Requires-Dist: pandas>=2.0
Provides-Extra: dev
Requires-Dist: pytest>=8.0; extra == "dev"
Requires-Dist: pytest-cov>=5.0; extra == "dev"
Dynamic: license-file
